gnntf/__init__.py
gnntf/measures.py
gnntf/core/__init__.py
gnntf/core/gnn/__init__.py
gnntf/core/gnn/gnn.py
gnntf/core/gnn/graph_manipulation.py
gnntf/core/gnn/graph_predictor.py
gnntf/core/gnn/architectures/__init__.py
gnntf/core/gnn/architectures/experimental.py
gnntf/core/gnn/architectures/filter.py
gnntf/core/gnn/architectures/gcn.py
gnntf/core/nn/__init__.py
gnntf/core/nn/batching.py
gnntf/core/nn/layered.py
gnntf/core/nn/layers.py
gnntf/core/nn/trainable.py
gnntf/core/nn/variables.py
gnntf/core/nn/architectures/__init__.py
gnntf/core/nn/architectures/mlp.py
gnntf-0.0.20.dist-info/METADATA
gnntf-0.0.20.dist-info/WHEEL
gnntf-0.0.20.dist-info/top_level.txt
gnntf-0.0.20.dist-info/RECORD
