Metadata-Version: 2.1
Name: gnntf
Version: 0.0.20
Summary: Graph neural networks on tensorflow
Home-page: https://github.com/maniospas/gnn-test
Author: Emmanouil (Manios) Krasanakis
Author-email: maniospas@hotmail.com
License: UNKNOWN
Platform: UNKNOWN
Classifier: Programming Language :: Python :: 3
Classifier: License :: OSI Approved :: Apache Software License
Classifier: Operating System :: OS Independent
Requires-Dist: sklearn
Requires-Dist: scipy
Requires-Dist: numpy
Requires-Dist: networkx
Requires-Dist: tensorflow
